leetcode/__init__.py
leetcode/config.py
leetcode/data_source.py
leetcode/model.py
leetcode/test_data_source.py
nonebot_plugin_leetcode-0.1.dist-info/METADATA
nonebot_plugin_leetcode-0.1.dist-info/WHEEL
nonebot_plugin_leetcode-0.1.dist-info/entry_points.txt
nonebot_plugin_leetcode-0.1.dist-info/top_level.txt
nonebot_plugin_leetcode-0.1.dist-info/RECORD
