Metadata-Version: 2.1
Name: nonebot-plugin-leetcode
Version: 0.1
Summary: one plugin used in nonebot , can send leetcode question to your qq friends and groups every day
Home-page: https://github.com/zxz0415/leetcode
Author: zxz0415
Author-email: 948125001@qq.com
License: UNKNOWN
Platform: UNKNOWN
Classifier: Programming Language :: Python :: 3
Classifier: Operating System :: OS Independent
Requires-Dist: nonebot-plugin-apscheduler (>=0.1.2)
Requires-Dist: nonebot2 (>=2.0.0.a16)
Requires-Dist: requests (>=2.26.0)
